miniwdl_omics_run/__init__.py
miniwdl_omics_run/__main__.py
miniwdl_omics_run/_version.py
miniwdl_omics_run-0.7.0.dist-info/licenses/LICENSE
miniwdl_omics_run-0.7.0.dist-info/METADATA
miniwdl_omics_run-0.7.0.dist-info/WHEEL
miniwdl_omics_run-0.7.0.dist-info/entry_points.txt
miniwdl_omics_run-0.7.0.dist-info/top_level.txt
miniwdl_omics_run-0.7.0.dist-info/RECORD
