Metadata-Version: 2.4
Name: miniwdl-omics-run
Version: 0.7.0
Summary: WDL launcher for Amazon Omics
Project-URL: repository, https://github.com/miniwdl-ext/miniwdl-omics-run.git
Classifier: License :: OSI Approved :: MIT License
Requires-Python: ~=3.8
License-File: LICENSE
Requires-Dist: miniwdl<2,>=1.9.1
Requires-Dist: boto3>=1.39
Provides-Extra: dev
Requires-Dist: setuptools; extra == "dev"
Requires-Dist: build; extra == "dev"
Requires-Dist: twine; extra == "dev"
Requires-Dist: pre-commit; extra == "dev"
Requires-Dist: ruff; extra == "dev"
Dynamic: license-file
